{
    "directors": [
        "Kevin Smith"
    ],
    "year": 2013,
    "synopsis": "From the singular mind of writer/director and podcaster Kevin Smith, and conceived from one of Smith's own Smodcast's, TUSK is a story unlike anything that has ever been committed to screen before. A tale that is equal parts hilarious and horrifying, TUSK will stay with you long after the credits roll.",
    "title": "Tusk",
    "countries": [
        "United States"
    ],
    "runtime": 102,
    "description": "Kevin Smith (Director), William Johnson (Producer), David Greathouse (Producer), Sam Englebardt (Producer)"
}