{
    "countries": [],
    "description": "Directors Noboru Iguchi, Yoshihiro Nishimura, Marcel Sarmiento, Jon Schnepp, Ernesto Diaz Espinosa, Adrian Garcia Bogliano, Ti West, Yudai Yamaguchi and Thomas Malling LIVE in attendance!",
    "directors": [
        "Kaare Andrews",
        "Ernesto Díaz Espinoza",
        "Angela Bettis",
        "Jason Eisener",
        "Bruno Forzani",
        "Héléne Cattet",
        "Adrián García Bogliano",
        "Xavier Gens",
        "Lee Hardcastle",
        "Jorge Michel Grau",
        "Noboru Iguchi",
        "Thomas Malling",
        "Yoshihiro Nishimura",
        "Banjong Pisathanakun",
        "Simon Rumley",
        "Marcel Sarmiento",
        "Jon Schnepp",
        "Srdjan Spasojevic",
        "Timo Tjahjanto",
        "Andrew Traucki",
        "Nacho Vigalondo",
        "Jake West",
        "Ti West",
        "Ben Wheatley",
        "Adam Wingard",
        "Yudai Yamaguchi"
    ],
    "meta": {
        "source_url": "http://fantasticfest.com/films/abcs-of-death"
    },
    "runtime": 123,
    "synopsis": "Twenty-six directors. Twenty-six ways to die. Co-produced by Drafthouse Films, and finally ready to be unleashed—see what happens when you give more than two dozen of the most brilliant filmmakers from around the world free reign to indulge their creative impulses and black humor. From A to Z, it's got something for every genre fan and is like nothing you've ever seen before.",
    "title": "The Abc's of Death",
    "year": 2012
}