{
    "countries": [],
    "description": "Director Charles de Lauzirika and actor Josh Lawson LIVE in attendane!",
    "directors": [
        "Charles de Lauzirika"
    ],
    "meta": {
        "source_url": "http://fantasticfest.com/films/crave"
    },
    "runtime": 113,
    "synopsis": "CRAVE follows a mentally unstable crime scene photographer on his descent into violence and madness. CRAVE won the New Flesh Award for Best First Feature at the 2012 edition of the Fantasia International Film Festival.",
    "title": "Crave",
    "year": 2012
}