{
  "countries": [
    "UNITED STATES"
  ],
  "description": "",
  "directors": [
    "Drew Goddard"
  ],
  "meta": {
    "source_url": "https://fantasticfest.com/films/bad-times-at-the-el-royale"
  },
  "runtime": null,
  "synopsis": "Seven strangers, each with a secret to bury, meet at Lake Tahoe's El Royale, a rundown hotel with a dark past. Over the course of one fateful night, everyone will have a last shot at redemption… before everything goes to hell. Jeff Bridges, Chris Hemsworth, Jon Hamm, Dakota Johnson and Cynthia Erivo lead an all-star cast in BAD TIMES AT THE EL ROYALE.",
  "title": "Bad Times At the el Royale",
  "year": 2018
}
